LICENSE
README.md
setup.py
linkedin_cat/__init__.py
linkedin_cat/api.py
linkedin_cat/base.py
linkedin_cat/helper.py
linkedin_cat/message.py
linkedin_cat/profile.py
linkedin_cat/search.py
linkedin_cat.egg-info/PKG-INFO
linkedin_cat.egg-info/SOURCES.txt
linkedin_cat.egg-info/dependency_links.txt
linkedin_cat.egg-info/requires.txt
linkedin_cat.egg-info/top_level.txt